frict/__init__.py
frict/lib.py
frict-0.1.1.dist-info/LICENSE
frict-0.1.1.dist-info/METADATA
frict-0.1.1.dist-info/WHEEL
frict-0.1.1.dist-info/RECORD
